dbcrust-0.22.5.dist-info/METADATA
dbcrust-0.22.5.dist-info/WHEEL
dbcrust-0.22.5.dist-info/entry_points.txt
dbcrust-0.22.5.dist-info/licenses/LICENSE
dbcrust/__init__.py
dbcrust/__main__.py
dbcrust/_internal.abi3.so
dbcrust/apps.py
dbcrust/client.py
dbcrust/connector.py
dbcrust/django/README.md
dbcrust/django/__init__.py
dbcrust/django/analyzer.py
dbcrust/django/apps.py
dbcrust/django/code_analyzer.py
dbcrust/django/database_helper.py
dbcrust/django/dbcrust_integration.py
dbcrust/django/debug_logging.py
dbcrust/django/example.py
dbcrust/django/example_middleware_usage.py
dbcrust/django/management/__init__.py
dbcrust/django/management/commands/__init__.py
dbcrust/django/management/commands/dbcrust.py
dbcrust/django/management/commands/dbcrust_analyze.py
dbcrust/django/middleware.py
dbcrust/django/pattern_detector.py
dbcrust/django/project_analyzer.py
dbcrust/django/query_collector.py
dbcrust/django/query_plan_analyzer.py
dbcrust/django/recommendations.py
dbcrust/django/test_enhanced_analyzer.py
dbcrust/django/test_middleware_demo.py
dbcrust/django/tests/__init__.py
dbcrust/django/tests/test_analyzer.py
dbcrust/django/tests/test_management_command.py
dbcrust/django/tests/test_middleware.py
dbcrust/django/troubleshoot_logging.py
dbcrust/django/utils.py
dbcrust/management/__init__.py
dbcrust/management/commands/__init__.py
dbcrust/management/commands/dbcrust.py
dbcrust-0.22.5.dist-info/RECORD
