Metadata-Version: 2.4
Name: dbcrust
Version: 0.22.5
Classifier: Development Status :: 4 - Beta
Classifier: Intended Audience :: Developers
Classifier: Intended Audience :: System Administrators
Classifier: License :: OSI Approved :: MIT License
Classifier: Operating System :: OS Independent
Classifier: Programming Language :: Python :: 3
Classifier: Programming Language :: Python :: 3.10
Classifier: Programming Language :: Python :: 3.11
Classifier: Programming Language :: Python :: 3.12
Classifier: Programming Language :: Python :: 3.13
Classifier: Programming Language :: Rust
Classifier: Topic :: Database
Classifier: Topic :: Database :: Front-Ends
Classifier: Topic :: Software Development :: Libraries :: Python Modules
Classifier: Topic :: Software Development :: Quality Assurance
Classifier: Topic :: System :: Systems Administration
Classifier: Topic :: Terminals
Classifier: Topic :: Utilities
Classifier: Environment :: Console
Classifier: Framework :: Django
Classifier: Intended Audience :: Information Technology
License-File: LICENSE
Summary: High-performance database CLI engineered for Django developers — Advanced ORM analysis, performance optimization, SSH tunneling, and seamless multi-database support (PostgreSQL, MySQL, SQLite)
Keywords: dbcrust,database,postgres,mysql,sqlite,cli,interactive,sql,postgresql,mysql,sqlite,ssh-tunnel,vault,docker,django,orm,python-library,performance-analysis,n-plus-one
Author-email: Clément Tourrière <clement.tourriere@gmail.com>
License: MIT
Requires-Python: >=3.10
Project-URL: Homepage, https://github.com/clement-tourriere/dbcrust
Project-URL: Repository, https://github.com/clement-tourriere/dbcrust
Project-URL: Documentation, https://github.com/clement-tourriere/dbcrust#readme
Project-URL: Changelog, https://github.com/clement-tourriere/dbcrust/blob/main/CHANGELOG.md
Project-URL: Bug Tracker, https://github.com/clement-tourriere/dbcrust/issues
Project-URL: Source Code, https://github.com/clement-tourriere/dbcrust
